<environmentvariabledefinition schemaname="glb_JournalDataSource">
  <apiid>/providers/microsoft.powerapps/apis/shared_sharepointonline</apiid>
  <defaultvalue>https://tekniklibartimy.sharepoint.com/sites/IT</defaultvalue>
  <displayname default="Journal Data Source">
    <label description="Journal Data Source" languagecode="1033" />
  </displayname>
  <introducedversion>1.0.0.0</introducedversion>
  <iscustomizable>1</iscustomizable>
  <isrequired>0</isrequired>
  <parameterkey>dataset</parameterkey>
  <secretstore>0</secretstore>
  <type>100000004</type>
</environmentvariabledefinition>